[
    {"_id":1,"title":"One","tasks":["First","second"]},
    {"_id":2,"title":"Two","tasks":["First","second"]},
    {"_id":3,"title":"Three","tasks":["First","second"]},
    {"_id":4,"title":"Four","tasks":["First","second"]},
    {"_id":5,"title":"Five","tasks":["First","second"]},
    {"_id":6,"title":"Six","tasks":["First","second"]},
    {"_id":7,"title":"Seven","tasks":["First","second"]},
    {"_id":8,"title":"One two","tasks":["First","second"]},
    {"_id":9,"title":"One three","tasks":["First","second"]},
    {"_id":10,"title":"One four","tasks":["First","second"]},
    {"_id":11,"title":"One five","tasks":["First","second"]},
    {"_id":12,"title":"One six","tasks":["First","second"]},
    {"_id":13,"title":"One seven","tasks":["First","second"]},
    {"_id":14,"title":"Two one","tasks":["First","second"]},
    {"_id":15,"title":"Three two","tasks":["First","second"]},
    {"_id":16,"title":"Three three","tasks":["First","second"]},
    {"_id":17,"title":"New title","tasks":["First","second"]}
]